mambo/README.md
mambo/__about__.py
mambo/__about__.pyc
mambo/__init__.py
mambo/__init__.pyc
mambo/cli.py
mambo/cli.pyc
mambo/kolibri.pyc
mambo/mambo.py
mambo/mambo.pyc
mambo/mambo.yml
mambo/md.pyc
mambo/md_ext.py
mambo/md_ext.pyc
mambo/publisher.pyc
mambo/utils.py
mambo/utils.pyc
mambo/yass.pyc
mambo/__pycache__/__about__.cpython-36.pyc
mambo/__pycache__/__init__.cpython-36.pyc
mambo/__pycache__/cli.cpython-36.pyc
mambo/__pycache__/mambo.cpython-36.pyc
mambo/__pycache__/md_ext.cpython-36.pyc
mambo/__pycache__/utils.cpython-36.pyc
mambo/skel/README.md
mambo/skel/error.log
mambo/skel/mambo.yml
mambo/skel/content/hello-world.md
mambo/skel/content/my_table.html
mambo/skel/content/blog/hello.md
mambo/skel/content/blog/index.html
mambo/skel/content/blog/world.md
mambo/skel/data/cars.json
mambo/skel/pages/about.html
mambo/skel/pages/advanced.html
mambo/skel/pages/blog.html
mambo/skel/pages/contact.html
mambo/skel/pages/error.html
mambo/skel/pages/index.html
mambo/skel/pages/articles/last.html
mambo/skel/static/main.css
mambo/skel/static/main.js
mambo/skel/static/_root/CNAME
mambo/skel/static/_root/robots.txt
mambo/skel/static/vendor/mambo.css
mambo/skel/static/vendor/milligram.css
mambo/skel/static/vendor/normalize.css
mambo/skel/templates/layouts/default.html
mambo/skel/templates/layouts/footer.html
mambo/skel/templates/layouts/header.html
mambo/skel/templates/macros/meta.html
mambo-1.3.1.dist-info/METADATA
mambo-1.3.1.dist-info/RECORD
mambo-1.3.1.dist-info/WHEEL
mambo-1.3.1.dist-info/entry_points.txt
mambo-1.3.1.dist-info/top_level.txt
