Metadata-Version: 2.1
Name: mambo
Version: 1.3.1
Summary: Mambo is an elegant and modern static site generator for the common folks!
Home-page: https://github.com/mardix/mambo
Author: Mardix
Author-email: mcx2082@gmail.com
License: MIT
Keywords: static site generator
Platform: any
Classifier: Environment :: Web Environment
Classifier: Intended Audience :: Developers
Classifier: License :: OSI Approved :: MIT License
Classifier: Operating System :: OS Independent
Classifier: Programming Language :: Python
Classifier: Programming Language :: Python :: 3
Classifier: Programming Language :: Python :: 3.3
Classifier: Programming Language :: Python :: 3.4
Classifier: Programming Language :: Python :: 3.5
Classifier: Programming Language :: Python :: 3.6
Classifier: Topic :: Internet :: WWW/HTTP :: Dynamic Content
Classifier: Topic :: Software Development :: Libraries :: Python Modules
Requires-Dist: jinja2 (==2.10.1)
Requires-Dist: click (==6.2)
Requires-Dist: pyyaml (==4.2b1)
Requires-Dist: markdown (==2.6.2)
Requires-Dist: python-frontmatter (==0.4.5)
Requires-Dist: htmlmin (==0.1.5)
Requires-Dist: livereload (==2.5.0)
Requires-Dist: arrow (==0.8.0)
Requires-Dist: python-slugify (==1.2.1)
Requires-Dist: pyScss
